mbtiles/__init__.py
mbtiles/cf.py
mbtiles/compat.py
mbtiles/mp.py
mbtiles/worker.py
mbtiles/scripts/__init__.py
mbtiles/scripts/cli.py
rio_mbtiles-1.6.0.dist-info/LICENSE
rio_mbtiles-1.6.0.dist-info/METADATA
rio_mbtiles-1.6.0.dist-info/WHEEL
rio_mbtiles-1.6.0.dist-info/entry_points.txt
rio_mbtiles-1.6.0.dist-info/top_level.txt
rio_mbtiles-1.6.0.dist-info/RECORD
