Metadata-Version: 2.1
Name: rio-mbtiles
Version: 1.6.0
Summary: A Rasterio plugin command that exports MBTiles
Home-page: https://github.com/mapbox/rio-mbtiles
Author: Sean Gillies
Author-email: sean@mapbox.com
License: MIT
Platform: UNKNOWN
Requires-Python: >=2.7.10
License-File: LICENSE
Requires-Dist: click
Requires-Dist: cligj (>=0.5)
Requires-Dist: mercantile
Requires-Dist: numpy (>=1.10)
Requires-Dist: rasterio (~=1.0)
Requires-Dist: shapely (~=1.7.0)
Requires-Dist: supermercado
Requires-Dist: tqdm (~=4.0)
Provides-Extra: test
Requires-Dist: coveralls ; extra == 'test'
Requires-Dist: pytest ; extra == 'test'
Requires-Dist: pytest-cov ; extra == 'test'
